{
  "transform": {
    "actor": 0,
    "type": "transform",
    "component_data": {
      "layer": "upper",
      "position": {
        "x": 0,
        "y": 0
      },
      "rotation": 0,
      "size": {
        "width": 20,
        "height": 20
      }
    }
  },
  "paint": {
    "actor": 0,
    "type": "paint",
    "component_data": {
      "color": {
        "r": 0,
        "g": 255,
        "b": 0,
        "a": 255
      }
    }
  },
  "destination": {
    "actor": 0,
    "type": "destination",
    "component_data": {
      "target": {
        "x": 0,
        "y": 0
      }
    }
  },
  "lifetime": {
    "actor": 0,
    "type": "lifetime",
    "component_data": {
      "milliseconds": 1000
    }
  },
  "movement_controller": {
    "type": "movement",
    "actor": 0,
    "component_data": {
      "owner": 0,
      "direction": {
        "x": 0,
        "y": 0
      },
      "speed": {
        "x": 0,
        "y": 0
      },
      "bound_by_map": false
    }
  },
  "behaviour": {
    "actor": 0,
    "type": "behaviour",
    "component_data": {
      "running_node": "none",
      "node_tree": {
        "type": "sequence",
        "node_data": {
          "children": [
            {
              "type": "move_forward",
              "node_data": {
                "distance": 2000,
                "distance_left": 2000
              }
            }
          ]
        }
      }
    }
  },
  "collider": {
    "actor": 0,
    "type": "collider",
    "component_data": {
      "layer": "projectile",
      "owner": 0,
      "collides_with": ["fighter", "ai", "destructable"]
    }
  },
  "damage": {
    "actor": 0,
    "type": "damage",
    "component_data": {
      "damage": 150,
      "on_hit_effect_paths": ["default"],
      "buff_debuff_paths": ["slow"],
      "piercing": false
    }
  },
  "stats": {
    "actor": 0,
    "type": "stats",
    "component_data": {
      "hp": 1,
      "max_hp": 1,
      "shield": 0,
      "max_shield": 0,
      "shield_regeneration": 0,
      "energy": 0,
      "energy_regeneration": 0,
      "power": 0,
      "armor": 0,
      "top_speed": 2000,
      "acceleration": 60000,
      "drag": 1
    }
  }
}
